xemu_perf_tester/__about__.py
xemu_perf_tester/__init__.py
xemu_perf_tester/runner.py
xemu_perf_tester/util/__init__.py
xemu_perf_tester/util/blocklist.py
xemu_perf_tester/util/github.py
xemu_perf_tester/util/hdd.py
xemu_perf_tester/util/perf_tester_config.py
xemu_perf_tester/util/xemu.py
xemu_perf_tester-0.2.5.dist-info/METADATA
xemu_perf_tester-0.2.5.dist-info/WHEEL
xemu_perf_tester-0.2.5.dist-info/entry_points.txt
xemu_perf_tester-0.2.5.dist-info/licenses/LICENSE
xemu_perf_tester-0.2.5.dist-info/RECORD
