Metadata-Version: 2.4
Name: xemu-perf-tester
Version: 0.2.5
Summary: Benchmark orchestrator for the xemu original Microsoft Xbox emulator
Project-URL: Documentation, https://github.com/abaire/xemu-perf-tester#readme
Project-URL: Issues, https://github.com/abaire/xemu-perf-tester/issues
Project-URL: Source, https://github.com/abaire/xemu-perf-tester
Author-email: Erik Abair <erik.abair@bearbrains.work>
License: This is free and unencumbered software released into the public domain.
License-File: LICENSE
Keywords: xbox,xemu
Classifier: Development Status :: 3 - Alpha
Classifier: Environment :: Console
Classifier: Intended Audience :: Developers
Classifier: Operating System :: OS Independent
Classifier: Programming Language :: Python
Classifier: Programming Language :: Python :: 3.10
Classifier: Programming Language :: Python :: 3.11
Classifier: Programming Language :: Python :: 3.12
Requires-Python: >=3.10
Requires-Dist: distro~=1.9.0
Requires-Dist: gitpython~=3.1.44
Requires-Dist: nxdk-pgraph-test-runner>=0.1.17
Requires-Dist: psutil~=7.0.0
Requires-Dist: py-cpuinfo~=9.0.0
Requires-Dist: py-machineid~=0.8.0
Requires-Dist: pyfatx~=0.0.7
Requires-Dist: python-xiso-repacker>=0.1.1
Requires-Dist: requests~=2.32.3
Requires-Dist: semver~=3.0.4
